fast_/Bugs.py
fast_/Cobol85Kind.py
fast_/Data.py
fast_/Delta.py
fast_/Element.py
fast_/Graph.py
fast_/Log.py
fast_/Pairs.py
fast_/Python3Kind.py
fast_/Slices.py
fast_/SmaliKind.py
fast_/SolidityKind.py
fast_/SrcmlKind.py
fast_/__init__.py
fast_/Data_/Anonymous3.py
fast_/Data_/__init__.py
fast_/Graph_/ContextEdges.py
fast_/Graph_/ContextGraph.py
fast_/Graph_/Edge.py
fast_/Graph_/NodeLabel.py
fast_/Graph_/NodeType.py
fast_/Graph_/SymbolCandidate.py
fast_/Graph_/Unit.py
fast_/Graph_/__init__.py
flatast/__init__.py
flatast/fast-json.py
flatast/fast_pb2.py
flatast/flatast2ggnn.py
flatast/json_format.py
flatast-0.0.14.post8.dist-info/METADATA
flatast-0.0.14.post8.dist-info/WHEEL
flatast-0.0.14.post8.dist-info/entry_points.txt
flatast-0.0.14.post8.dist-info/top_level.txt
flatast-0.0.14.post8.dist-info/RECORD
