Metadata-Version: 2.1
Name: flatast
Version: 0.0.14.post8
Summary: Converting Flattened AST to Gated Graph Neural Networks
Home-page: https://bitbucket.org/yijunyu/fast
Author: Yijun Yu
Author-email: y.yu@open.ac.uk
License: Apache 2.0
Platform: UNKNOWN
Requires: flatbuffers
Requires: protobuf
Requires-Dist: flatbuffers
Requires-Dist: protobuf
